[{"_path":"/ctf/2022-hsctf9","title":"HSCTF 9","description":"Transferred here @2024","created":"2024-06-11T01:36","updated":"2024-07-07T22:23","_id":"content:ctf:2022-HSCTF9:index.md"},{"_path":"/ctf/2022-hsctf9/web-gallery","title":"Web Gallery","description":"","created":"2024-06-11T01:36","updated":"2024-06-11T01:38","_id":"content:ctf:2022-HSCTF9:web-gallery.md"},{"_path":"/ctf/2022-hsctf9/directory-egg-hunt","title":"","description":"","_id":"content:ctf:2022-HSCTF9:directory-egg-hunt:index.md"},{"_path":"/ctf/2022-hsctf9/guess-the-flag","title":"","description":"","created":"2024-06-11T01:36","updated":"2024-06-11T01:38","_id":"content:ctf:2022-HSCTF9:guess-the-flag:index.md"},{"_path":"/ctf/2022-hsctf9/pass","title":"","description":"","created":"2024-06-11T01:36","updated":"2024-06-11T01:38","_id":"content:ctf:2022-HSCTF9:pass:index.md"},{"_path":"/ctf/2022-hsctf9/travelling-salesman","title":"","description":"","_id":"content:ctf:2022-HSCTF9:travelling-salesman:index.md"}]