{"_path":"/blog/2024-11-12","_dir":"blog","_draft":false,"_partial":false,"_locale":"","title":"2024-11-12T00:00:00.000Z","description":"My first blog.","tags":["blog"],"created":"2024-11-12T16:18","updated":"2024-11-12T17:23","readingTime":{"text":"1 min read","minutes":0.02,"time":1200,"words":4},"body":{"type":"root","children":[{"type":"element","tag":"p","props":{},"children":[{"type":"text","value":"My first blog."}]},{"type":"element","tag":"p","props":{},"children":[{"type":"text","value":"Nothing special."}]},{"type":"element","tag":"p","props":{},"children":[{"type":"element","tag":"img","props":{"alt":"giphy.gif","src":"https://res.cloudinary.com/kumonochisanaka/image/upload/v1731450187/2024/11/cc03de86d39be8c509e15a7bed3f4a1e.gif"},"children":[]}]}],"toc":{"title":"","searchDepth":2,"depth":2,"links":[]}},"_type":"markdown","_id":"content:blog:2024-11-12.md","_source":"content","_file":"blog/2024-11-12.md","_stem":"blog/2024-11-12","_extension":"md"}